README.md
setup.py
kurekdev_hello_world.egg-info/PKG-INFO
kurekdev_hello_world.egg-info/SOURCES.txt
kurekdev_hello_world.egg-info/dependency_links.txt
kurekdev_hello_world.egg-info/top_level.txt
sample_package/__init__.py
sample_package/sample.py